apmecclient/__init__.py
apmecclient/client.py
apmecclient/i18n.py
apmecclient/shell.py
apmecclient/version.py
apmecclient/apmec/__init__.py
apmecclient/apmec/client.py
apmecclient/apmec/v1_0/__init__.py
apmecclient/apmec/v1_0/extension.py
apmecclient/apmec/v1_0/events/__init__.py
apmecclient/apmec/v1_0/events/events.py
apmecclient/apmec/v1_0/mem/__init__.py
apmecclient/apmec/v1_0/mem/mea.py
apmecclient/apmec/v1_0/mem/mead.py
apmecclient/apmec/v1_0/meo/__init__.py
apmecclient/apmec/v1_0/meo/meca.py
apmecclient/apmec/v1_0/meo/mecad.py
apmecclient/apmec/v1_0/meo/vim.py
apmecclient/apmec/v1_0/meo/vim_utils.py
apmecclient/apmec/v1_0/meso/__init__.py
apmecclient/apmec/v1_0/meso/mes.py
apmecclient/apmec/v1_0/meso/mesd.py
apmecclient/common/__init__.py
apmecclient/common/_i18n.py
apmecclient/common/clientmanager.py
apmecclient/common/command.py
apmecclient/common/constants.py
apmecclient/common/exceptions.py
apmecclient/common/extension.py
apmecclient/common/serializer.py
apmecclient/common/utils.py
apmecclient/common/validators.py
apmecclient/tests/__init__.py
apmecclient/tests/unit/__init__.py
apmecclient/tests/unit/test_cli10.py
apmecclient/tests/unit/test_utils.py
apmecclient/tests/unit/vm/__init__.py
apmecclient/tests/unit/vm/test_cli10_vim.py
apmecclient/tests/unit/vm/test_vim_utils.py
apmecclient/tests/unit/vm/samples/vim_config.yaml
apmecclient/tests/unit/vm/samples/vim_config_without_auth_url.yaml
apmecclient/v1_0/__init__.py
apmecclient/v1_0/client.py
python_apmecclient-0.1.0.dist-info/DESCRIPTION.rst
python_apmecclient-0.1.0.dist-info/METADATA
python_apmecclient-0.1.0.dist-info/RECORD
python_apmecclient-0.1.0.dist-info/WHEEL
python_apmecclient-0.1.0.dist-info/entry_points.txt
python_apmecclient-0.1.0.dist-info/metadata.json
python_apmecclient-0.1.0.dist-info/pbr.json
python_apmecclient-0.1.0.dist-info/top_level.txt
