Metadata-Version: 2.0
Name: python-apmecclient
Version: 0.1.0
Summary: CLI and Client Library for OpenStack Apmec
Home-page: http://docs.openstack.org/developer/apmec/
Author: OpenStack
Author-email: openstack-dev@lists.openstack.org
License: UNKNOWN
Platform: UNKNOWN
Classifier: Environment :: OpenStack
Classifier: Intended Audience :: Developers
Classifier: Intended Audience :: Information Technology
Classifier: Intended Audience :: System Administrators
Classifier: License :: OSI Approved :: Apache Software License
Classifier: Operating System :: POSIX :: Linux
Classifier: Programming Language :: Python
Classifier: Programming Language :: Python :: 2
Classifier: Programming Language :: Python :: 2.7
Classifier: Programming Language :: Python :: 3
Classifier: Programming Language :: Python :: 3.5
Requires-Dist: Babel (>=2.3.4,!=2.4.0)
Requires-Dist: cliff (!=2.9.0,>=2.8.0)
Requires-Dist: iso8601 (>=0.1.11)
Requires-Dist: netaddr (>=0.7.18)
Requires-Dist: oslo.i18n (>=3.15.3)
Requires-Dist: oslo.log (>=3.30.0)
Requires-Dist: oslo.serialization (!=2.19.1,>=2.18.0)
Requires-Dist: oslo.utils (>=3.28.0)
Requires-Dist: pbr (!=2.1.0,>=2.0.0)
Requires-Dist: python-keystoneclient (>=3.8.0)
Requires-Dist: requests (>=2.14.2)
Requires-Dist: simplejson (>=3.5.1)
Requires-Dist: six (>=1.9.0)
Requires-Dist: stevedore (>=1.20.0)
